pynearshore/__init__.py
pynearshore/current_dynamics.py
pynearshore/data_io.py
pynearshore/numerical_methods.py
pynearshore/physical_constants.py
pynearshore/radiation_stress.py
pynearshore/sediment_transport.py
pynearshore/solver.py
pynearshore/solver_comparison.py
pynearshore/wave_models.py
pynearshore/wave_propagation.py
pynearshore-2.0.0.dist-info/licenses/AUTHORS
pynearshore-2.0.0.dist-info/licenses/LICENSE
tests/__init__.py
tests/test_data_io.py
tests/test_numerical_methods.py
tests/test_sediment_transport.py
tests/test_wave_models.py
pynearshore-2.0.0.dist-info/METADATA
pynearshore-2.0.0.dist-info/WHEEL
pynearshore-2.0.0.dist-info/top_level.txt
pynearshore-2.0.0.dist-info/RECORD
