Metadata-Version: 2.4
Name: pynearshore
Version: 2.0.0
Summary: Nearshore wave propagation, currents, and sediment transport modeling
Home-page: https://github.com/pavlishenku/pynearshore
Author: Pavlishenku
Author-email: pavlishenku@gmail.com
Project-URL: Bug Reports, https://github.com/pavlishenku/pynearshore/issues
Project-URL: Source, https://github.com/pavlishenku/pynearshore
Keywords: coastal engineering,wave propagation,sediment transport,nearshore dynamics,wave breaking,Goda model,Battjes-Janssen,Bailard model,numerical methods,Runge-Kutta,oceanography
Classifier: Development Status :: 4 - Beta
Classifier: Intended Audience :: Science/Research
Classifier: Intended Audience :: Education
Classifier: Topic :: Scientific/Engineering :: Physics
Classifier: Topic :: Scientific/Engineering :: Hydrology
Classifier: License :: OSI Approved :: MIT License
Classifier: Programming Language :: Python :: 3
Classifier: Programming Language :: Python :: 3.7
Classifier: Programming Language :: Python :: 3.8
Classifier: Programming Language :: Python :: 3.9
Classifier: Programming Language :: Python :: 3.10
Classifier: Programming Language :: Python :: 3.11
Classifier: Programming Language :: Python :: 3.12
Classifier: Operating System :: OS Independent
Classifier: Natural Language :: English
Requires-Python: >=3.7
License-File: LICENSE
License-File: AUTHORS
Requires-Dist: numpy>=1.19.0
Requires-Dist: scipy>=1.5.0
Provides-Extra: viz
Requires-Dist: matplotlib>=3.0.0; extra == "viz"
Requires-Dist: seaborn>=0.11.0; extra == "viz"
Provides-Extra: dev
Requires-Dist: pytest>=6.0; extra == "dev"
Requires-Dist: pytest-cov>=2.0; extra == "dev"
Requires-Dist: black>=21.0; extra == "dev"
Requires-Dist: flake8>=3.9; extra == "dev"
Requires-Dist: mypy>=0.900; extra == "dev"
Dynamic: author
Dynamic: author-email
Dynamic: classifier
Dynamic: description
Dynamic: description-content-type
Dynamic: home-page
Dynamic: keywords
Dynamic: license-file
Dynamic: project-url
Dynamic: provides-extra
Dynamic: requires-dist
Dynamic: requires-python
Dynamic: summary
